stream_processor/__init__.py
stream_processor/api/__init__.py
stream_processor/api/actions.py
stream_processor/api/decorator.py
stream_processor/engine/__init__.py
stream_processor/engine/context.py
stream_processor/engine/exceptions.py
stream_processor/engine/history.py
stream_processor/engine/processor.py
stream_processor/engine/registry.py
stream_processor/engine/trie.py
stream_processor/engine/types.py
llm_stream_processor-0.1.0.dist-info/LICENSE
llm_stream_processor-0.1.0.dist-info/METADATA
llm_stream_processor-0.1.0.dist-info/WHEEL
llm_stream_processor-0.1.0.dist-info/top_level.txt
llm_stream_processor-0.1.0.dist-info/RECORD
