Metadata-Version: 2.1
Name: llm-stream-processor
Version: 0.1.0
Summary: A callback-driven, prefix-safe, lazy LLM stream sanitization library.
Author-email: Rohan Kumar <rohanvermadev@gmail.com>
License: MIT
Project-URL: Homepage, https://github.com/DevOpRohan/llm_stream_processor
Project-URL: Repository, https://github.com/DevOpRohan/llm_stream_processor
Project-URL: Documentation, https://github.com/DevOpRohan/llm_stream_processor#readme
Project-URL: Issues, https://github.com/DevOpRohan/llm_stream_processor/issues
Keywords: llm,stream,processing,sanitization,streaming,callback,content-filtering,redaction,aho-corasick,openai,chatgpt
Classifier: Development Status :: 4 - Beta
Classifier: Intended Audience :: Developers
Classifier: License :: OSI Approved :: MIT License
Classifier: Operating System :: OS Independent
Classifier: Programming Language :: Python :: 3
Classifier: Programming Language :: Python :: 3.7
Classifier: Programming Language :: Python :: 3.8
Classifier: Programming Language :: Python :: 3.9
Classifier: Programming Language :: Python :: 3.10
Classifier: Programming Language :: Python :: 3.11
Classifier: Programming Language :: Python :: 3.12
Classifier: Topic :: Software Development :: Libraries :: Python Modules
Classifier: Topic :: Text Processing :: Filters
Classifier: Topic :: Scientific/Engineering :: Artificial Intelligence
Requires-Python: >=3.7
License-File: LICENSE
Provides-Extra: dev
Requires-Dist: pytest>=7.0; extra == "dev"
Requires-Dist: pytest-cov>=4.0; extra == "dev"
Requires-Dist: pytest-asyncio>=0.21; extra == "dev"
Requires-Dist: black>=23.0; extra == "dev"
Requires-Dist: flake8>=6.0; extra == "dev"
Requires-Dist: mypy>=1.0; extra == "dev"
